generate_dockerignore.py
generate_dockerignore_from_gitignore-0.1.3.dist-info/entry_points.txt
generate_dockerignore_from_gitignore-0.1.3.dist-info/WHEEL
generate_dockerignore_from_gitignore-0.1.3.dist-info/METADATA
generate_dockerignore_from_gitignore-0.1.3.dist-info/RECORD
