Metadata-Version: 2.1
Name: generate-dockerignore-from-gitignore
Version: 0.1.3
Summary: .dockerignore file generator based on .gitignore file(s)
Author-email: Tim Vergenz <vergenzt@gmail.com>
